discord/ext/cluster/__init__.py
discord/ext/cluster/client.py
discord/ext/cluster/cluster.py
discord/ext/cluster/errors.py
discord/ext/cluster/objects.py
discord/ext/cluster/shard.py
better_cluster-1.0.0.dist-info/LICENSE
better_cluster-1.0.0.dist-info/METADATA
better_cluster-1.0.0.dist-info/WHEEL
better_cluster-1.0.0.dist-info/top_level.txt
better_cluster-1.0.0.dist-info/RECORD
