Metadata-Version: 2.1
Name: better-cluster
Version: 1.0.0
Summary: A high-performance inter-process communication library designed to handle communication between multiple shards
Home-page: https://github.com/MiroslavRosenov/better-cluster
Author: DaPandaOfficial
Author-email: miroslav.rosenov39@gmail.com
License: MIT License
Project-URL: Source, https://github.com/MiroslavRosenov/better-cluster
Project-URL: Issue Tracker, https://github.com/MiroslavRosenov/better-cluster/issues
Keywords: better-cluster,cluster,python,discord.py
Classifier: Development Status :: 5 - Production/Stable
Classifier: Framework :: AsyncIO
Classifier: Intended Audience :: Developers
Classifier: License :: OSI Approved :: MIT License
Classifier: Natural Language :: English
Classifier: Operating System :: OS Independent
Classifier: Programming Language :: Python
Classifier: Programming Language :: Python :: 3.8
Classifier: Programming Language :: Python :: 3.9
Classifier: Programming Language :: Python :: 3.10
Classifier: Topic :: Communications
Classifier: Topic :: Internet
Classifier: Topic :: Software Development
Classifier: Topic :: Software Development :: Libraries
Classifier: Topic :: Software Development :: Libraries :: Python Modules
Requires-Python: >=3.8.0
License-File: LICENSE
